jobs_detector/__init__.py
jobs_detector/exceptions.py
jobs_detector/main.py
jobs_detector/settings.py
rmotr_b7_c2_g1_jobs_detector-0.0.1.dist-info/DESCRIPTION.rst
rmotr_b7_c2_g1_jobs_detector-0.0.1.dist-info/METADATA
rmotr_b7_c2_g1_jobs_detector-0.0.1.dist-info/RECORD
rmotr_b7_c2_g1_jobs_detector-0.0.1.dist-info/WHEEL
rmotr_b7_c2_g1_jobs_detector-0.0.1.dist-info/metadata.json
rmotr_b7_c2_g1_jobs_detector-0.0.1.dist-info/top_level.txt
